{
    "service":"xyz.openbmc_project.Inventory.Manager",
    "root_path":"/xyz/openbmc_project/inventory",
    "entities":[
        {
            "interface" : "xyz.openbmc_project.Inventory.Item.Board.Motherboard",
            "entity_type" : 64
        },
        {
            "interface" : "xyz.openbmc_project.Inventory.Item.Bmc",
            "entity_type" : 137
        },
        {
            "interface" : "xyz.openbmc_project.Inventory.Item.Panel",
            "entity_type" : 69
        },
        {
            "interface" : "xyz.openbmc_project.Inventory.Item.Vrm",
            "entity_type" : 123
        },
        {
            "interface" : "xyz.openbmc_project.Inventory.Item.Tpm",
            "entity_type" : 24576
        },
        {
            "interface" : "xyz.openbmc_project.Inventory.Item.System",
            "entity_type" : 11521
        },
        {
            "interface" : "xyz.openbmc_project.Inventory.Item.Chassis",
            "entity_type" : 45
        },
        {
            "interface" : "xyz.openbmc_project.Inventory.Item.PowerSupply",
            "entity_type" : 120
        }
    ]
}
